insarviz/__init__.py
insarviz/__logging__.py
insarviz/__main__.py
insarviz/__prelude__.py
insarviz/version.py
insarviz/icons/WMS.svg
insarviz/icons/arrowdown.png
insarviz/icons/arrowup.png
insarviz/icons/cursor.png
insarviz/icons/eye_closed.svg
insarviz/icons/eye_icons_template.svg
insarviz/icons/eye_open.svg
insarviz/icons/icons8-help.png
insarviz/icons/logo_insarviz.png
insarviz/icons/points.png
insarviz/icons/profile.png
insarviz/icons/raster1B.svg
insarviz/icons/rasterRGB.svg
insarviz/icons/redo.svg
insarviz/icons/ref.png
insarviz/icons/remove.png
insarviz/icons/spatial.svg
insarviz/icons/swipetool.png
insarviz/icons/temporal.svg
insarviz/icons/undo.svg
insarviz/misc/Base10Increments.py
insarviz/misc/Bound.py
insarviz/misc/ComputedValue.py
insarviz/misc/DEMTexture.py
insarviz/misc/GLProgram.py
insarviz/misc/Matrix.py
insarviz/misc/Point.py
insarviz/misc/Qt.py
insarviz/misc/Threads.py
insarviz/misc/__init__.py
insarviz/misc/__prelude__.py
insarviz/misc/bresenham.py
insarviz/shaders/Shader.py
insarviz/shaders/__init__.py
insarviz/shaders/__prelude__.py
insarviz/shaders/hsv_rgb.glsl
insarviz/shaders/geo_map/fragment.glsl
insarviz/shaders/geo_map/vertex.glsl
insarviz/shaders/map/fragment.glsl
insarviz/shaders/map/tess_control.glsl
insarviz/shaders/map/tess_eval.glsl
insarviz/shaders/map/utils.glsl
insarviz/shaders/map/vertex.glsl
insarviz/shaders/minimap/fragment.glsl
insarviz/shaders/minimap/vertex.glsl
insarviz/shaders/profile/image/fragment.glsl
insarviz/shaders/profile/image/vertex.glsl
insarviz/shaders/profile/line/fragment.glsl
insarviz/shaders/profile/line/vertex.glsl
insarviz/shaders/tile/fragment.glsl
insarviz/shaders/tile/vertex.glsl
insarviz/shaders/viewport_rect/fragment.glsl
insarviz/shaders/viewport_rect/vertex.glsl
insarviz/state/ColorMap.py
insarviz/state/Dataset.py
insarviz/state/MapPoint.py
insarviz/state/MapProfile.py
insarviz/state/SelectedBand.py
insarviz/state/WindowState.py
insarviz/state/__init__.py
insarviz/state/__prelude__.py
insarviz-3.0.2.3.dist-info/licenses/AUTHORS.rst
insarviz-3.0.2.3.dist-info/licenses/LICENSE.txt
insarviz-3.0.2.3.dist-info/METADATA
insarviz-3.0.2.3.dist-info/WHEEL
insarviz-3.0.2.3.dist-info/entry_points.txt
insarviz-3.0.2.3.dist-info/top_level.txt
insarviz-3.0.2.3.dist-info/RECORD
